runningtrack/__init__.py
runningtrack/changes.py
runningtrack/config.py
runningtrack/const.py
runningtrack/dates.py
runningtrack/log.py
runningtrack/track.py
runningtrack-0.4.7.dist-info/LICENSE
runningtrack-0.4.7.dist-info/METADATA
runningtrack-0.4.7.dist-info/WHEEL
runningtrack-0.4.7.dist-info/top_level.txt
runningtrack-0.4.7.dist-info/RECORD
