Metadata-Version: 2.1
Name: runningtrack
Version: 0.4.7
Summary: Runs functions in the background and tracks them
Home-page: https://paulopes.github.io/running/
Author: Paulo Lopes
Author-email: palopes@cisco.com
License: UNKNOWN
Platform: UNKNOWN
